{
	"dialogue": [
		{
			"sound": "",
			"speed": 0.05,
			"portrait": "gf",
			"boxState": "normal",
			"expression": "talk",
			"text": "You did great red head!"
		},
		{
			"sound": "",
			"speed": 0.05,
			"portrait": "gf",
			"boxState": "normal",
			"expression": "talk",
			"text": "I don't know why are y-"
		},
		{
			"sound": "",
			"speed": 0.05,
			"portrait": "bf",
			"boxState": "normal",
			"expression": "talk",
			"text": "*placeholder* Did i misunderstood something?"
		},
		{
			"sound": "",
			"speed": 0.05,
			"portrait": "bf",
			"boxState": "normal",
			"expression": "confused",
			"text": "And who the fuck are you?"
		},
		{
			"sound": "",
			"speed": 0.05,
			"portrait": "bf",
			"boxState": "normal",
			"expression": "excited",
			"text": "beep"
		},
		{
			"sound": "",
			"speed": 0.05,
			"portrait": "bf",
			"boxState": "normal",
			"expression": "confused",
			"text": "What?"
		},
		{
			"sound": "",
			"speed": 0.05,
			"portrait": "bf",
			"boxState": "normal",
			"expression": "excited",
			"text": "beep bop skoodop"
		},
		{
			"sound": "",
			"speed": 0.05,
			"portrait": "bf",
			"boxState": "normal",
			"expression": "talk",
			"text": "beepa boopo"
		},
		{
			"sound": "",
			"speed": 0.1,
			"portrait": "bf",
			"boxState": "normal",
			"expression": "talk",
			"text": "Interesting..."
		},
		{
			"sound": "",
			"speed": 0.05,
			"portrait": "bf",
			"boxState": "normal",
			"expression": "confused",
			"text": "I did not understand shit thought, I think that's ur language or something."
		},
		{
			"sound": "",
			"speed": 0.05,
			"portrait": "bf",
			"boxState": "normal",
			"expression": "pissed",
			"text": "What a shame, that ur the only one and last one."
		},
		{
			"sound": "",
			"speed": 0.05,
			"portrait": "gf",
			"boxState": "normal",
			"expression": "confused",
			"text": "Why are you allways like this..."
		},
		{
			"sound": "",
			"speed": 0.05,
			"portrait": "bf",
			"boxState": "normal",
			"expression": "talk",
			"text": "Even if ur an 'Adult' now, doesn't mean you have all the rights."
		},
		{
			"sound": "",
			"speed": 0.05,
			"portrait": "bf",
			"boxState": "normal",
			"expression": "talk",
			"text": "To use MY property for getting ur new boyfriends."
		},
		{
			"sound": "",
			"speed": 0.05,
			"portrait": "bf",
			"boxState": "normal",
			"expression": "talk",
			"text": "You know that I kill them anyway and this one will be gone as well."
		},
		{
			"sound": "",
			"speed": 0.16,
			"portrait": "gf",
			"boxState": "normal",
			"expression": "shocked",
			"text": "..."
		},
		{
			"sound": "",
			"speed": 0.05,
			"portrait": "gf",
			"boxState": "normal",
			"expression": "confused",
			"text": "I am just attached to him way differently..."
		},
		{
			"sound": "",
			"speed": 0.05,
			"portrait": "bf",
			"boxState": "normal",
			"expression": "excited",
			"text": "ify skebap"
		},
		{
			"sound": "",
			"speed": 0.05,
			"portrait": "bf",
			"boxState": "normal",
			"expression": "confused",
			"text": "Alright let's make a deal. "
		},
		{
			"sound": "",
			"speed": 0.05,
			"portrait": "bf",
			"boxState": "normal",
			"expression": "talk",
			"text": "if he's gonna somehow show me of what capable he-"
		},
		{
			"sound": "",
			"speed": 0.125,
			"portrait": "gf",
			"boxState": "normal",
			"expression": "demon",
			"text": "Oh I know!"
		},
		{
			"sound": "",
			"speed": 0.05,
			"portrait": "bf",
			"boxState": "normal",
			"expression": "excited",
			"text": "skeedap boop beep! "
		},
		{
			"sound": "",
			"speed": 0.05,
			"portrait": "bf",
			"boxState": "normal",
			"expression": "confused",
			"text": "A... Mic?"
		},
		{
			"sound": "",
			"speed": 0.05,
			"portrait": "bf",
			"boxState": "normal",
			"expression": "excited",
			"text": "peeeeb!"
		},
		{
			"sound": "",
			"speed": 0.05,
			"portrait": "gf",
			"boxState": "normal",
			"expression": "demon",
			"text": "Doesn't it give you a answear already? "
		},
		{
			"sound": "",
			"speed": 0.05,
			"portrait": "bf",
			"boxState": "normal",
			"expression": "confused",
			"text": "But did not sing for so long, memories hit hard."
		},
		{
			"sound": "",
			"speed": 0.05,
			"portrait": "bf",
			"boxState": "normal",
			"expression": "pissed",
			"text": "Hmm alright let's see if u gonna keep up with me."
		},
		{
			"sound": "",
			"speed": 0.05,
			"portrait": "bf",
			"boxState": "normal",
			"expression": "excited",
			"text": "Bop!"
		}
	]
}